jarvis/__init__.py
jarvis/config/__init__.py
jarvis/config/openai.py
jarvis/config/silero.py
jarvis/config/sound.py
jarvis/config/vosk.py
jarvis/gpt/__init__.py
jarvis/gpt/context.py
jarvis/gpt/primitives.py
jarvis/silero/__init__.py
jarvis/vosk_/__init__.py
jarvis/whisper/__init__.py
jarvis/whisper/inputs.py
jarvis/whisper/outputs.py
jarvis_toolkit-0.0.4.dist-info/LICENSE
jarvis_toolkit-0.0.4.dist-info/METADATA
jarvis_toolkit-0.0.4.dist-info/WHEEL
jarvis_toolkit-0.0.4.dist-info/top_level.txt
jarvis_toolkit-0.0.4.dist-info/RECORD
