Metadata-Version: 2.1
Name: jarvis-toolkit
Version: 0.0.4
Summary: Jarvis Toolkit
Author-email: Artur Aliiev <pastordev@jarvis-toolkit.com>
Project-URL: Homepage, https://bitbucket.org/jarvis-toolkit/jarvis-core/src/master/t
Classifier: Programming Language :: Python :: 3
Classifier: License :: OSI Approved :: MIT License
Classifier: Operating System :: OS Independent
Requires-Python: >=3.10
License-File: LICENSE
Requires-Dist: email-validator (==1.3.1)
Requires-Dist: ffmpeg (==1.4)
Requires-Dist: gTTS (==2.3.1)
Requires-Dist: openai
Requires-Dist: PyAudio (==0.2.13)
Requires-Dist: pydantic (==1.10.4)
Requires-Dist: pydub (==0.25.1)
Requires-Dist: SpeechRecognition (==3.9.0)
Requires-Dist: vosk (==0.3.45)
Requires-Dist: nltk
Requires-Dist: numpy
Requires-Dist: silero
